{
  "url": "https://www.wikihow.com/Mute-a-Chat-on-WhatsApp",
  "title": "How to Mute a Chat on WhatsApp",
  "steps": [
    {
      "title": "Open your WhatsApp app.",
      "content": "Open your WhatsApp app."
    },
    {
      "title": "Tap the \"Chats\" tab.",
      "content": "Tap the \"Chats\" tab. This is in the toolbar at the bottom of your screen; you may have to tap the backward-facing arrow in the top left corner of your screen to view this toolbar."
    },
    {
      "title": "Swipe left on the chat you wish to mute.",
      "content": "Swipe left on the chat you wish to mute. You should see two options--\"More\" and \"Archive\"--appear on the right side of the screen."
    },
    {
      "title": "Tap More.",
      "content": "Tap More ."
    },
    {
      "title": "Tap Mute.",
      "content": "Tap Mute ."
    },
    {
      "title": "Tap a mute time frame.",
      "content": "Tap a mute time frame. You can choose \"8 hours\", \"1 week\", or \"1 year\". You have successfully muted a chat on WhatsApp! To unmute the conversation manually, tap Mute again and then tap Unmute ."
    },
    {
      "title": "Open your WhatsApp app.",
      "content": "Open your WhatsApp app."
    },
    {
      "title": "Tap the \"Chats\" tab.",
      "content": "Tap the \"Chats\" tab. This is in the toolbar at the top of your screen. You may have to tap the backward-facing arrow in the top left corner of your screen to view this toolbar."
    },
    {
      "title": "Tap a conversation.",
      "content": "Tap a conversation."
    },
    {
      "title": "Tap ⋮.",
      "content": "Tap ⋮ ."
    },
    {
      "title": "Tap Mute.",
      "content": "Tap Mute ."
    },
    {
      "title": "Tap a mute time frame.",
      "content": "Tap a mute time frame. You can choose \"8 hours\", \"1 week\", or \"1 year\". You have successfully muted a chat on WhatsApp! To unmute the conversation manually, tap Mute again and then tap Unmute ."
    }
  ]
}