{
  "url": "https://www.wikihow.com/Fold-an-Origami-Sail-Boat",
  "title": "How to Fold an Origami Sail Boat",
  "steps": [
    {
      "title": "Obtain a piece of 8 1/2 x 11 inch computer paper.",
      "content": "Obtain a piece of 8 1/2 x 11 inch computer paper."
    },
    {
      "title": "Fold it in half.",
      "content": "Fold it in half."
    },
    {
      "title": "Fold down the corners to make a triangle",
      "content": "Fold down the corners to make a triangle ."
    },
    {
      "title": "Fold the bottom flaps over the edge of the triangle",
      "content": "Fold the bottom flaps over the edge of the triangle on both sides to form an origami hat."
    },
    {
      "title": "Flatten by opening the figure and folding the right and left corners together.",
      "content": "Flatten by opening the figure and folding the right and left corners together."
    },
    {
      "title": "Fold the bottom up about 2 inches (5.1 cm), front and back.",
      "content": "Fold the bottom up about 2 inches (5.1 cm), front and back."
    },
    {
      "title": "Flatten again by opening the figure and folding the right and left corners together.",
      "content": "Flatten again by opening the figure and folding the right and left corners together."
    },
    {
      "title": "Fold the bottom about an inch up.",
      "content": "Fold the bottom about an inch up."
    },
    {
      "title": "Unfold to reveal the creases.",
      "content": "Unfold to reveal the creases."
    },
    {
      "title": "Pull the corners out.",
      "content": "Pull the corners out. There you have it – a Sailboat!"
    }
  ]
}