{
  "url": "https://www.wikihow.com/Install-Software-Silently-(Unattended)",
  "title": "How to Install Software Silently (Unattended)",
  "steps": [
    {
      "title": "Download the software that you want to install.",
      "content": "Download the software that you want to install. Put it into any folder. For example, if you wanted to install Adobe Reader , download it and put it into your \"C:\\FPAC_Installer\" folder."
    },
    {
      "title": "Open the Command prompt.",
      "content": "Open the Command prompt . Go to the Run, type \"cmd\" and press \"enter\" to open command prompt."
    },
    {
      "title": "Navigate to the folder where you kept the software EXE file.",
      "content": "Navigate to the folder where you kept the software EXE file. For example, the \"C:\\FPAC_Installer\" mentioned earlier."
    },
    {
      "title": "Select the software.exe file.",
      "content": "Select the software.exe file. Use this command: \"softwarename.exe /?\". This command will check for all the switches which have been defined by the software manufacturer for this software."
    },
    {
      "title": "Wait for all the switches to appear.",
      "content": "Wait for all the switches to appear. As you want to install the software silently, find the switch available for silent installation."
    },
    {
      "title": "Use this command to use the silent switch:",
      "content": "Use this command to use the silent switch: \"softwarename.exe /switch\"."
    },
    {
      "title": "Once you are done with the silent switch command, sit back and relax.",
      "content": "Once you are done with the silent switch command, sit back and relax. Your software will get installed automatically."
    }
  ]
}