{
  "url": "https://www.wikihow.com/Access-Your-SD-Card-on-Samsung-Galaxy",
  "title": "How to Access Your SD Card on Samsung Galaxy",
  "steps": [
    {
      "title": "Swipe down on the notification bar.",
      "content": "Swipe down on the notification bar."
    },
    {
      "title": "Tap on the Settings icon.",
      "content": "Tap on the Settings icon. It’s the gear at the top of the screen."
    },
    {
      "title": "Tap on Application manager.",
      "content": "Tap on Application manager . It’s located towards the middle of the page."
    },
    {
      "title": "Swipe left.",
      "content": "Swipe left. Doing so will bring you to a list of apps stored on your SD card where you can manage them from there."
    },
    {
      "title": "Tap the app you want to manage.",
      "content": "Tap the app you want to manage."
    },
    {
      "title": "Tap on Move to SD card.",
      "content": "Tap on Move to SD card . Doing so will transfer the app to external storage. You will need a microSD card inserted in your device for this to work."
    },
    {
      "title": "Tap on Move to Device Storage.",
      "content": "Tap on Move to Device Storage . This will move the app back to your internal storage."
    },
    {
      "title": "Tap Uninstall.",
      "content": "Tap Uninstall . Doing so will completely remove the app from your device and you’ll have managed your applications by accessing the SD card."
    }
  ]
}