{
  "url": "https://www.wikihow.com/Draw-Pyramids",
  "title": "How to Draw Pyramids",
  "steps": [
    {
      "title": "For instance, it might be 5 by 5 cm (2.0 by 2.0 in).",
      "content": "For instance, it might be 5 by 5 cm (2.0 by 2.0 in)."
    },
    {
      "title": "Sketch the 5 centimeter (2.0 in) line.",
      "content": "Sketch the 5 centimeter (2.0 in) line. Using your compass, measure from the point to the pencil at 5 centimeter (2.0 in)."
    },
    {
      "title": "Put your compass at one end of your baseline.",
      "content": "Put your compass at one end of your baseline. Doing this, draw part of a circle. Repeat with the other end of the baseline. Doing this, you should have both lines crossing in the middle. This part is difficult, but don't worry."
    },
    {
      "title": "You should end up with a triangle.",
      "content": "You should end up with a triangle."
    },
    {
      "title": "Rub out the lines you used in part 3.",
      "content": "Rub out the lines you used in part 3."
    },
    {
      "title": "To one side, draw an extension like another side like in Fig.3.",
      "content": "To one side, draw an extension like another side like in Fig.3. Make sure the baseline of that side is above the first baseline you drew."
    }
  ]
}