{
  "url": "https://www.wikihow.com/Summon-Golden-Freddy-in-Five-Nights-at-Freddy%27s",
  "title": "How to Summon Golden Freddy in Five Nights at Freddy's",
  "steps": [
    {
      "title": "Start a night.",
      "content": "Start a night. Then open the monitor and go to CAM 2B (West Hall Corner) and flip the monitor up and down until you see a poster of a close-up of Golden Freddy's face. Note that this method does not work on Android devices."
    },
    {
      "title": "Close the monitor when you see the poster.",
      "content": "Close the monitor when you see the poster. You'll see Golden Freddy sitting in front of you."
    },
    {
      "title": "Flip up the monitor.",
      "content": "Flip up the monitor. If you want him to kill you, just leave him there for a few seconds, but opening the monitor is the only way (besides completing a night) for him to disappear."
    },
    {
      "title": "Beat Night 6.",
      "content": "Beat Night 6. You have now unlocked the Custom Night, go into the menu."
    },
    {
      "title": "Enter 1/9/8/7 into the AI settings.",
      "content": "Enter 1/9/8/7 into the AI settings."
    },
    {
      "title": "Press \"READY.\"",
      "content": "Press \"READY.\" This will cause Golden Freddy's kill screen to appear and, once again, crash/freeze your game."
    }
  ]
}