{
  "url": "https://www.wikihow.com/Make-a-Bathroom-a-Steamroom",
  "title": "How to Make a Bathroom a Steamroom",
  "steps": [
    {
      "title": "Make sure there's proper ventilation.",
      "content": "Make sure there's proper ventilation. This is crucial to preventing mold and mildew growth."
    },
    {
      "title": "Turn the shower on as hot as possible.",
      "content": "Turn the shower on as hot as possible."
    },
    {
      "title": "Open the shower curtain.",
      "content": "Open the shower curtain."
    },
    {
      "title": "Close the door.",
      "content": "Close the door."
    },
    {
      "title": "Bring in a chair with arms for safety and relaxation.",
      "content": "Bring in a chair with arms for safety and relaxation. Don't sit on a toilet, as it could be slippery."
    },
    {
      "title": "Do not enter the scalding hot water.",
      "content": "Do not enter the scalding hot water. Sit away from the sources."
    }
  ]
}