{
  "url": "https://www.wikihow.com/Draw-a-Table",
  "title": "How to Draw a Table",
  "steps": [
    {
      "title": "Draw a rectangular prism as shown in the picture.",
      "content": "Draw a rectangular prism as shown in the picture."
    },
    {
      "title": "Divide the sides of the rectangular prism into (approximately) equal vertical bars.",
      "content": "Divide the sides of the rectangular prism into (approximately) equal vertical bars."
    },
    {
      "title": "Divide the sides of the rectangular prism into (approximately) equal horizontal bars.",
      "content": "Divide the sides of the rectangular prism into (approximately) equal horizontal bars."
    },
    {
      "title": "For this step:",
      "content": "For this step: Clear the black lines. Draw additional green lines. Keep the red lines."
    },
    {
      "title": "Clean up the work.",
      "content": "Clean up the work. Here is your table. Enjoy!"
    },
    {
      "title": "Draw a parallelogram.",
      "content": "Draw a parallelogram."
    },
    {
      "title": "Draw three lines below the parallelogram.",
      "content": "Draw three lines below the parallelogram."
    },
    {
      "title": "Draw curves below the lines drawn earlier.",
      "content": "Draw curves below the lines drawn earlier."
    },
    {
      "title": "Based on the outline, draw the dining table.",
      "content": "Based on the outline, draw the dining table."
    },
    {
      "title": "Add details to the dining table.",
      "content": "Add details to the dining table."
    },
    {
      "title": "Erase the unnecessary outlines.",
      "content": "Erase the unnecessary outlines."
    },
    {
      "title": "Color your dining table!",
      "content": "Color your dining table!"
    }
  ]
}