{
  "url": "https://www.wikihow.com/Draw-a-Realistic-Eye",
  "title": "How to Draw a Realistic Eye",
  "steps": [
    {
      "title": "Draw the shape of the eye.",
      "content": "Draw the shape of the eye."
    },
    {
      "title": "Draw the details for the pupils, iris and eyebrows.",
      "content": "Draw the details for the pupils, iris and eyebrows."
    },
    {
      "title": "Draw the details for the eyelashes, pupil highlights, iris and eyebrows.",
      "content": "Draw the details for the eyelashes, pupil highlights, iris and eyebrows."
    },
    {
      "title": "Apply light shading over the drawing to simulate light shadows.",
      "content": "Apply light shading over the drawing to simulate light shadows."
    },
    {
      "title": "Complete the drawing by using a darker shade to fill areas with darker shadows.",
      "content": "Complete the drawing by using a darker shade to fill areas with darker shadows."
    },
    {
      "title": "Draw the shape of the eye.",
      "content": "Draw the shape of the eye. Use magazines of photographs as guides for drawing different types of eyes. This is step one."
    },
    {
      "title": "Draw the Pupil and the Iris.",
      "content": "Draw the Pupil and the Iris."
    },
    {
      "title": "Draw in the additional details.",
      "content": "Draw in the additional details."
    },
    {
      "title": "Use a darker shade to draw over the artwork.",
      "content": "Use a darker shade to draw over the artwork."
    },
    {
      "title": "Apply a light gray tone or shade over the eye",
      "content": "Apply a light gray tone or shade over the eye"
    },
    {
      "title": "Apply a slightly darker shade for light shadowed areas.",
      "content": "Apply a slightly darker shade for light shadowed areas."
    },
    {
      "title": "Apply a darker shade of gray for darker areas or you could try to shade in to the little details.",
      "content": "Apply a darker shade of gray for darker areas or you could try to shade in to the little details."
    },
    {
      "title": "Apply the darkest gray for areas with very dark shadows (but not black).",
      "content": "Apply the darkest gray for areas with very dark shadows (but not black)."
    },
    {
      "title": "Blend the edges of each layer of gray to simulate a realistic eye using shades of gray.",
      "content": "Blend the edges of each layer of gray to simulate a realistic eye using shades of gray."
    }
  ]
}